LICENSE
MANIFEST.in
README.rst
requirements.txt
setup.py
DockDel/__init__.py
DockDel/cli.py
DockDel/essai.py
DockDel.egg-info/PKG-INFO
DockDel.egg-info/SOURCES.txt
DockDel.egg-info/dependency_links.txt
DockDel.egg-info/entry_points.txt
DockDel.egg-info/requires.txt
DockDel.egg-info/top_level.txt