Metadata-Version: 1.1
Name: DockDel
Version: 0.1.1-alpha
Summary: Didel command-line tool
Home-page: https://github.com/tsalmon/DockDel
Author: Salmon Thomas
Author-email: ths871@gmail.com
License: The MIT License (MIT)
